setup.cfg
setup.py
remchecker/__init__.py
remchecker.egg-info/PKG-INFO
remchecker.egg-info/SOURCES.txt
remchecker.egg-info/dependency_links.txt
remchecker.egg-info/entry_points.txt
remchecker.egg-info/not-zip-safe
remchecker.egg-info/requires.txt
remchecker.egg-info/top_level.txt