Metadata-Version: 1.0
Name: remchecker
Version: 0.1dev
Summary: check followers remove
Home-page: UNKNOWN
Author: seikichi
Author-email: seikichi@kmc.gr.jp
License: MIT
Keywords: twitter remove
Platform: UNKNOWN
Classifier: Development Status :: 3 - Alpha
Classifier: Environment :: Console
Classifier: Intended Audience :: End Users/Desktop
Classifier: License :: OSI Approved :: MIT License
Classifier: Natural Language :: Japanese
Classifier: Programming Language :: Python
Classifier: Topic :: Communications
